setup.cfg
setup.py
aggregation_builder/__init__.py
aggregation_builder/query_builder.py
aggregation_builder/query_set.py
aggregation_builder.egg-info/PKG-INFO
aggregation_builder.egg-info/SOURCES.txt
aggregation_builder.egg-info/dependency_links.txt
aggregation_builder.egg-info/requires.txt
aggregation_builder.egg-info/top_level.txt
aggregation_builder/operators/__init__.py
aggregation_builder/operators/arithmetic.py
aggregation_builder/operators/array.py
aggregation_builder/operators/boolean.py
aggregation_builder/operators/comparison.py
aggregation_builder/operators/date.py
aggregation_builder/operators/group.py
aggregation_builder/operators/other.py
aggregation_builder/operators/set.py
aggregation_builder/operators/string.py