Metadata-Version: 1.1
Name: aggregation-builder
Version: 0.0.4
Summary: Package that implements a simple mongodb aggregation builder.
Home-page: https://github.com/MosesSymeonidis/aggregation_builder
Author: Moses Symeonidis
Author-email: msymewnidhs2113@yahoo.gr
License: LICENSE
Download-URL: https://github.com/MosesSymeonidis/aggregation_builder/archive/master.tar.gz
Keywords: mongodb,aggregation
Platform: UNKNOWN
